examples/3bit_memory_analysis.py
examples/3bit_memory_fps.py
examples/3bit_memory_train.py
examples/3bit_memory_visualisation.py
examples/__init__.py
examples/initialization.py
examples/multi_region_connectivity.py
examples/three_bit_memory.py
imgs/3bit.png
pyrnn/__init__.py
pyrnn/_io.py
pyrnn/_plot.py
pyrnn/_progress.py
pyrnn/_rnn.py
pyrnn/_trainer.py
pyrnn/_utils.py
pyrnn/connectivity.py
pyrnn/linalg.py
pyrnn/plot.py
pyrnn/render.py
pyrnn/rnn.py
pyrnn/weights.py
pyrnn/analysis/__init__.py
pyrnn/analysis/dimensionality.py
pyrnn/analysis/fixed.py
pyrnn/analysis/fixed_connectivity.py
pyrnn-0.0.7.dist-info/LICENSE
pyrnn-0.0.7.dist-info/METADATA
pyrnn-0.0.7.dist-info/WHEEL
pyrnn-0.0.7.dist-info/top_level.txt
pyrnn-0.0.7.dist-info/RECORD
