Metadata-Version: 2.1
Name: pyrnn
Version: 0.0.7
Summary: Pytorch implementation of vanilla RNN
Home-page: https://github.com/FedeClaudi/pyrnn
Author: Federico Claudi
License: UNKNOWN
Platform: UNKNOWN
Requires-Python: >=3.6,
Requires-Dist: rich (>=9.0.0)
Requires-Dist: pyinspect
Requires-Dist: matplotlib
Requires-Dist: seaborn
Requires-Dist: torch
Requires-Dist: numpy
Requires-Dist: networkx
Requires-Dist: myterial
Requires-Dist: einops
Requires-Dist: loguru
Requires-Dist: vedo
Provides-Extra: dev
Requires-Dist: coverage-badge ; extra == 'dev'
